{
  "manifest": "analysis/symbols/gameplay-functions.json",
  "root": "analysis/decompile",
  "function_count": 3,
  "bn_index": "analysis/decompile/binja/index.json",
  "ida_index": "analysis/decompile/ida/index.json",
  "bn_exported": 3,
  "ida_exported": 3,
  "bn_mismatch_count": 0,
  "ida_mismatch_count": 0,
  "total_mismatch_count": 0,
  "has_mismatches": false,
  "sync_ida_symbols": false,
  "health_check_ran": true,
  "strict": true,
  "selected_functions": [
    {
      "name": "update_subgame_camera",
      "address": "0x446020"
    },
    {
      "name": "initialize_cutscene_ai",
      "address": "0x446130"
    },
    {
      "name": "update_cutscene",
      "address": "0x4466d0"
    }
  ],
  "health_check_count": 91,
  "health_failing_check_count": 0,
  "health_passed": true,
  "health_config": "analysis/decompile/health_checks.json"
}
