{
  "manifest": "analysis/symbols/gameplay-functions.json",
  "root": "analysis/decompile",
  "function_count": 9,
  "bn_index": "analysis/decompile/binja/index.json",
  "ida_index": "analysis/decompile/ida/index.json",
  "bn_exported": 9,
  "ida_exported": 9,
  "bn_mismatch_count": 0,
  "ida_mismatch_count": 0,
  "total_mismatch_count": 0,
  "has_mismatches": false,
  "sync_ida_symbols": false,
  "binja_refreshed": true,
  "ida_refreshed": true,
  "health_check_ran": true,
  "strict": true,
  "selected_functions": [
    {
      "name": "load_x_mesh",
      "address": "0x405640"
    },
    {
      "name": "load_or_reuse_cached_x_mesh",
      "address": "0x405cc0"
    },
    {
      "name": "load_x_animation_clip",
      "address": "0x405d60"
    },
    {
      "name": "refresh_object_vertex_buffer",
      "address": "0x412250"
    },
    {
      "name": "initialize_object_distort",
      "address": "0x41aa30"
    },
    {
      "name": "apply_distort_to_object",
      "address": "0x41aa50"
    },
    {
      "name": "build_all_objects",
      "address": "0x42f9e0"
    },
    {
      "name": "calc_object_bounding_box",
      "address": "0x42fb10"
    },
    {
      "name": "calc_object_texture_groups",
      "address": "0x4303f0"
    }
  ],
  "health_check_count": 754,
  "health_failing_check_count": 0,
  "health_passed": true,
  "health_config": "analysis/decompile/health_checks.json"
}
